MANIFEST.in
README.txt
setup.cfg
setup.py
anthill/__init__.py
anthill.skinner.egg-info/PKG-INFO
anthill.skinner.egg-info/SOURCES.txt
anthill.skinner.egg-info/dependency_links.txt
anthill.skinner.egg-info/entry_points.txt
anthill.skinner.egg-info/namespace_packages.txt
anthill.skinner.egg-info/not-zip-safe
anthill.skinner.egg-info/requires.txt
anthill.skinner.egg-info/top_level.txt
anthill/skinner/__init__.py
anthill/skinner/config.py
anthill/skinner/configure.zcml
anthill/skinner/handler.py
anthill/skinner/interfaces.py
anthill/skinner/permissions.zcml
anthill/skinner/tests.py
anthill/skinner/browser/.navigation.py.swp
anthill/skinner/browser/__init__.py
anthill/skinner/browser/configure.zcml
anthill/skinner/browser/handling.py
anthill/skinner/browser/interfaces.py
anthill/skinner/browser/navigation.py
anthill/skinner/profiles/skinner/actions.xml
anthill/skinner/profiles/skinner/skins.xml
anthill/skinner/skins/anthill_skinner_templates/main_template.pt
anthill/skinner/templates/__init__.py
anthill/skinner/templates/base_skinner_theme.py
anthill/skinner/templates/base_skinner_theme/+project+-configure.zcml_tmpl
anthill/skinner/templates/base_skinner_theme/MANIFEST.in_tmpl
anthill/skinner/templates/base_skinner_theme/+namespace_package+/+package+/configure.zcml_tmpl
anthill/skinner/templates/base_skinner_theme/+namespace_package+/+package+/profiles.zcml_tmpl
anthill/skinner/templates/base_skinner_theme/+namespace_package+/+package+/setuphandlers.py_tmpl
anthill/skinner/templates/base_skinner_theme/+namespace_package+/+package+/skins.zcml_tmpl
anthill/skinner/templates/base_skinner_theme/+namespace_package+/+package+/version.txt_tmpl
anthill/skinner/templates/base_skinner_theme/+namespace_package+/+package+/browser/__init__.py
anthill/skinner/templates/base_skinner_theme/+namespace_package+/+package+/browser/configure.zcml_tmpl
anthill/skinner/templates/base_skinner_theme/+namespace_package+/+package+/browser/interfaces.py_tmpl
anthill/skinner/templates/base_skinner_theme/+namespace_package+/+package+/browser/navigation.py
anthill/skinner/templates/base_skinner_theme/+namespace_package+/+package+/browser/viewlet.pt_tmpl
anthill/skinner/templates/base_skinner_theme/+namespace_package+/+package+/browser/viewlets.py_tmpl
