Metadata-Version: 1.0
Name: anthill.skinner
Version: 0.8
Summary: Skinning for plone made easy
Home-page: http://www.banality.de
Author: Simon Pamies
Author-email: s.pamies@banality.de
License: GPL
Keywords: skinning theming plone zope
Platform: UNKNOWN
Classifier: Framework :: Plone
Classifier: Programming Language :: Python
Classifier: Topic :: Software Development :: Libraries :: Python Modules
